pysalesforceutils.py
webservice.py
pysalesforceutils-1.0.14.dist-info/LICENSE
pysalesforceutils-1.0.14.dist-info/METADATA
pysalesforceutils-1.0.14.dist-info/WHEEL
pysalesforceutils-1.0.14.dist-info/top_level.txt
pysalesforceutils-1.0.14.dist-info/RECORD
