Metadata-Version: 2.1
Name: pysalesforceutils
Version: 1.0.14
Summary: Python module to wrap the Salesforce APIs
Home-page: https://github.com/gbarger/PySalesforce
Author: Glen Barger
Author-email: gbarger@gmail.com
License: UNKNOWN
Platform: UNKNOWN
License-File: LICENSE
Requires-Dist: requests
Requires-Dist: urllib3
Requires-Dist: zeep
